{
  "id": "F066",
  "普通名稱": "貝芬替",
  "廠牌名稱": null,
  "通過日期": null,
  "licenses": [
    {
      "許可證字": "農藥原製",
      "許可證號": "00081",
      "中文名稱": "貝芬替",
      "農藥代號": "F066",
      "英文名稱": "CARBENDAZIM",
      "廠牌名稱": null,
      "化學成分": "methyl benzimidazol-2-ylcarbamate",
      "國外原製造廠商": null,
      "有效期限": "110/08/18",
      "廠商名稱": "興農股份有限公司",
      "農藥使用範圍": "http://data.coa.gov.tw:80/Service/OpenData/FromM/PesticideDetail.aspx?ltyp=30&lno=00081"
    },
    {
      "許可證字": "農藥原製",
      "許可證號": "00089",
      "中文名稱": "貝芬替",
      "農藥代號": "F066",
      "英文名稱": "CARBENDAZIM",
      "廠牌名稱": null,
      "化學成分": "methyl benzimidazol-2-ylcarbamate",
      "國外原製造廠商": null,
      "有效期限": "110/08/23",
      "廠商名稱": "富農化學工業股份有限公司",
      "農藥使用範圍": "http://data.coa.gov.tw:80/Service/OpenData/FromM/PesticideDetail.aspx?ltyp=30&lno=00089"
    },
    {
      "許可證字": "農藥進",
      "許可證號": "00100",
      "中文名稱": "貝芬替",
      "農藥代號": "F066",
      "英文名稱": "CARBENDAZIM",
      "廠牌名稱": "倍多芬",
      "化學成分": "methyl benzimidazol-2-ylcarbamate",
      "國外原製造廠商": "\" DIANA \" GEROGE SERVOS & CO. S. A.",
      "有效期限": "103/03/17",
      "廠商名稱": "發順企業股份有限公司",
      "農藥使用範圍": "http://data.coa.gov.tw:80/Service/OpenData/FromM/PesticideDetail.aspx?ltyp=20&lno=00100"
    },
    {
      "許可證字": "農藥製",
      "許可證號": "00112",
      "中文名稱": "貝芬替",
      "農藥代號": "F066",
      "英文名稱": "CARBENDAZIM",
      "廠牌名稱": "殺菌讚",
      "化學成分": "methyl benzimidazol-2-ylcarbamate",
      "國外原製造廠商": null,
      "有效期限": "112/11/19",
      "廠商名稱": "國豐化學工業股份有限公司",
      "農藥使用範圍": "http://data.coa.gov.tw:80/Service/OpenData/FromM/PesticideDetail.aspx?ltyp=10&lno=00112"
    },
    {
      "許可證字": "農藥製",
      "許可證號": "00575",
      "中文名稱": "貝芬替",
      "農藥代號": "F066",
      "英文名稱": "CARBENDAZIM",
      "廠牌名稱": "菌絕-８００",
      "化學成分": "methyl benzimidazol-2-ylcarbamate",
      "國外原製造廠商": null,
      "有效期限": "113/09/09",
      "廠商名稱": "日農科技股份有限公司",
      "農藥使用範圍": "http://data.coa.gov.tw:80/Service/OpenData/FromM/PesticideDetail.aspx?ltyp=10&lno=00575"
    },
    {
      "許可證字": "農藥進",
      "許可證號": "00601",
      "中文名稱": "貝芬替",
      "農藥代號": "F066",
      "英文名稱": "CARBENDAZIM",
      "廠牌名稱": "大露產",
      "化學成分": "methyl benzimidazol-2-ylcarbamate",
      "國外原製造廠商": "SUNDAT (S) PTE LTD.",
      "有效期限": "109/05/15",
      "廠商名稱": "生力化學工業股份有限公司",
      "農藥使用範圍": "http://data.coa.gov.tw:80/Service/OpenData/FromM/PesticideDetail.aspx?ltyp=20&lno=00601"
    },
    {
      "許可證字": "農藥原進",
      "許可證號": "00720",
      "中文名稱": "貝芬替",
      "農藥代號": "F066",
      "英文名稱": "CARBENDAZIM",
      "廠牌名稱": null,
      "化學成分": "methyl benzimidazol-2-ylcarbamate",
      "國外原製造廠商": "JIANGSU LANFENG BIOCHEMICAL CO., LTD.",
      "有效期限": "108/07/31",
      "廠商名稱": "富農化學工業股份有限公司",
      "農藥使用範圍": "http://data.coa.gov.tw:80/Service/OpenData/FromM/PesticideDetail.aspx?ltyp=40&lno=00720"
    },
    {
      "許可證字": "農藥原進",
      "許可證號": "00783",
      "中文名稱": "貝芬替",
      "農藥代號": "F066",
      "英文名稱": "CARBENDAZIM",
      "廠牌名稱": null,
      "化學成分": "methyl benzimidazol-2-ylcarbamate",
      "國外原製造廠商": "ANHUI GUANGXIN AGROCHEMICAL CO., LTD.",
      "有效期限": "112/09/03",
      "廠商名稱": "興農股份有限公司",
      "農藥使用範圍": "http://data.coa.gov.tw:80/Service/OpenData/FromM/PesticideDetail.aspx?ltyp=40&lno=00783"
    },
    {
      "許可證字": "農藥原進",
      "許可證號": "00861",
      "中文名稱": "貝芬替",
      "農藥代號": "F066",
      "英文名稱": "CARBENDAZIM",
      "廠牌名稱": null,
      "化學成分": "methyl benzimidazol-2-ylcarbamate",
      "國外原製造廠商": "NINGXIA WYNCA TECHNOLOGY CO., LTD.",
      "有效期限": "111/12/17",
      "廠商名稱": "青山貿易有限公司",
      "農藥使用範圍": "http://data.coa.gov.tw:80/Service/OpenData/FromM/PesticideDetail.aspx?ltyp=40&lno=00861"
    },
    {
      "許可證字": "農藥進",
      "許可證號": "01161",
      "中文名稱": "貝芬替",
      "農藥代號": "F066",
      "英文名稱": "CARBENDAZIM",
      "廠牌名稱": "松巴司丁",
      "化學成分": "methyl benzimidazol-2-ylcarbamate",
      "國外原製造廠商": "KRISHI RASAYAN (BIHAR)",
      "有效期限": "110/04/17",
      "廠商名稱": "松樹國際有限公司",
      "農藥使用範圍": "http://data.coa.gov.tw:80/Service/OpenData/FromM/PesticideDetail.aspx?ltyp=20&lno=01161"
    },
    {
      "許可證字": "農藥進",
      "許可證號": "01294",
      "中文名稱": "貝芬替",
      "農藥代號": "F066",
      "英文名稱": "CARBENDAZIM",
      "廠牌名稱": "大力產",
      "化學成分": "methyl benzimidazol-2-ylcarbamate",
      "國外原製造廠商": "ARYSTA LIFESCIENCE OUGREE PRODUCTION SPRL",
      "有效期限": "112/08/05",
      "廠商名稱": "德方有限公司",
      "農藥使用範圍": "http://data.coa.gov.tw:80/Service/OpenData/FromM/PesticideDetail.aspx?ltyp=20&lno=01294"
    },
    {
      "許可證字": "農藥進",
      "許可證號": "01458",
      "中文名稱": "貝芬替",
      "農藥代號": "F066",
      "英文名稱": "CARBENDAZIM",
      "廠牌名稱": "蘋果大樂剷",
      "化學成分": "methyl benzimidazol-2-ylcarbamate",
      "國外原製造廠商": "PT. BIOWORLD BIOSCIENCES MANUFACTURING INDUSTRIES",
      "有效期限": "109/01/04",
      "廠商名稱": "松樹國際有限公司",
      "農藥使用範圍": "http://data.coa.gov.tw:80/Service/OpenData/FromM/PesticideDetail.aspx?ltyp=20&lno=01458"
    },
    {
      "許可證字": "農藥進",
      "許可證號": "01555",
      "中文名稱": "貝芬替",
      "農藥代號": "F066",
      "英文名稱": "CARBENDAZIM",
      "廠牌名稱": "克利斯丁",
      "化學成分": "methyl benzimidazol-2-ylcarbamate",
      "國外原製造廠商": "DEVIDAYAL (SALES) LIMITED",
      "有效期限": "109/12/08",
      "廠商名稱": "耕得貿易股份有限公司",
      "農藥使用範圍": "http://data.coa.gov.tw:80/Service/OpenData/FromM/PesticideDetail.aspx?ltyp=20&lno=01555"
    },
    {
      "許可證字": "農藥進",
      "許可證號": "01695",
      "中文名稱": "貝芬替",
      "農藥代號": "F066",
      "英文名稱": "CARBENDAZIM",
      "廠牌名稱": "倍多芬",
      "化學成分": "methyl benzimidazol-2-ylcarbamate",
      "國外原製造廠商": "VIETNAM PESTICIDE JOINT-STOCK COMPANY",
      "有效期限": "111/09/20",
      "廠商名稱": "瑞泓生技有限公司",
      "農藥使用範圍": "http://data.coa.gov.tw:80/Service/OpenData/FromM/PesticideDetail.aspx?ltyp=20&lno=01695"
    },
    {
      "許可證字": "農藥製",
      "許可證號": "01701",
      "中文名稱": "貝芬替",
      "農藥代號": "F066",
      "英文名稱": "CARBENDAZIM",
      "廠牌名稱": "貝斯王",
      "化學成分": "methyl benzimidazol-2-ylcarbamate",
      "國外原製造廠商": null,
      "有效期限": "109/04/21",
      "廠商名稱": "利台化學工業股份有限公司",
      "農藥使用範圍": "http://data.coa.gov.tw:80/Service/OpenData/FromM/PesticideDetail.aspx?ltyp=10&lno=01701"
    },
    {
      "許可證字": "農藥製",
      "許可證號": "01833",
      "中文名稱": "貝芬替",
      "農藥代號": "F066",
      "英文名稱": "CARBENDAZIM",
      "廠牌名稱": "保粒大",
      "化學成分": "methyl benzimidazol-2-ylcarbamate",
      "國外原製造廠商": null,
      "有效期限": "109/04/30",
      "廠商名稱": "興農股份有限公司",
      "農藥使用範圍": "http://data.coa.gov.tw:80/Service/OpenData/FromM/PesticideDetail.aspx?ltyp=10&lno=01833"
    },
    {
      "許可證字": "農藥進",
      "許可證號": "02018",
      "中文名稱": "貝芬替",
      "農藥代號": "F066",
      "英文名稱": "CARBENDAZIM",
      "廠牌名稱": "達仙",
      "化學成分": "methyl benzimidazol-2-ylcarbamate",
      "國外原製造廠商": "SULPHUR MILLS LIMITED",
      "有效期限": "110/06/01",
      "廠商名稱": "瑞福企業有限公司",
      "農藥使用範圍": "http://data.coa.gov.tw:80/Service/OpenData/FromM/PesticideDetail.aspx?ltyp=20&lno=02018"
    },
    {
      "許可證字": "農藥進",
      "許可證號": "02031",
      "中文名稱": "貝芬替",
      "農藥代號": "F066",
      "英文名稱": "CARBENDAZIM",
      "廠牌名稱": "新巴斯丁",
      "化學成分": "methyl benzimidazol-2-ylcarbamate",
      "國外原製造廠商": "BASF SOCIETAS EUROPAEA",
      "有效期限": "105/07/26",
      "廠商名稱": "台灣巴斯夫股份有限公司",
      "農藥使用範圍": "http://data.coa.gov.tw:80/Service/OpenData/FromM/PesticideDetail.aspx?ltyp=20&lno=02031"
    },
    {
      "許可證字": "農藥製",
      "許可證號": "02213",
      "中文名稱": "貝芬替",
      "農藥代號": "F066",
      "英文名稱": "CARBENDAZIM",
      "廠牌名稱": "好果青",
      "化學成分": "methyl benzimidazol-2-ylcarbamate",
      "國外原製造廠商": null,
      "有效期限": "109/11/04",
      "廠商名稱": "嘉農企業股份有限公司",
      "農藥使用範圍": "http://data.coa.gov.tw:80/Service/OpenData/FromM/PesticideDetail.aspx?ltyp=10&lno=02213"
    },
    {
      "許可證字": "農藥製",
      "許可證號": "02236",
      "中文名稱": "貝芬替",
      "農藥代號": "F066",
      "英文名稱": "CARBENDAZIM",
      "廠牌名稱": null,
      "化學成分": "methyl benzimidazol-2-ylcarbamate",
      "國外原製造廠商": null,
      "有效期限": "109/11/16",
      "廠商名稱": "台灣正豐植保股份有限公司",
      "農藥使用範圍": "http://data.coa.gov.tw:80/Service/OpenData/FromM/PesticideDetail.aspx?ltyp=10&lno=02236"
    },
    {
      "許可證字": "農藥進",
      "許可證號": "02256",
      "中文名稱": "貝芬替",
      "農藥代號": "F066",
      "英文名稱": "CARBENDAZIM",
      "廠牌名稱": "好派",
      "化學成分": "methyl benzimidazol-2-ylcarbamate",
      "國外原製造廠商": "IMASPRO RESOURCES SDN. BHD.",
      "有效期限": "110/11/06",
      "廠商名稱": "高事達農化有限公司",
      "農藥使用範圍": "http://data.coa.gov.tw:80/Service/OpenData/FromM/PesticideDetail.aspx?ltyp=20&lno=02256"
    },
    {
      "許可證字": "農藥製",
      "許可證號": "02265",
      "中文名稱": "貝芬替",
      "農藥代號": "F066",
      "英文名稱": "CARBENDAZIM",
      "廠牌名稱": "保速金",
      "化學成分": "methyl benzimidazol-2-ylcarbamate",
      "國外原製造廠商": null,
      "有效期限": "109/05/29",
      "廠商名稱": "好速化學股份有限公司",
      "農藥使用範圍": "http://data.coa.gov.tw:80/Service/OpenData/FromM/PesticideDetail.aspx?ltyp=10&lno=02265"
    },
    {
      "許可證字": "農藥製",
      "許可證號": "02382",
      "中文名稱": "貝芬替",
      "農藥代號": "F066",
      "英文名稱": "CARBENDAZIM",
      "廠牌名稱": null,
      "化學成分": "methyl benzimidazol-2-ylcarbamate",
      "國外原製造廠商": null,
      "有效期限": "109/08/03",
      "廠商名稱": "臺灣庵原農藥股份有限公司",
      "農藥使用範圍": "http://data.coa.gov.tw:80/Service/OpenData/FromM/PesticideDetail.aspx?ltyp=10&lno=02382"
    },
    {
      "許可證字": "農藥進",
      "許可證號": "02464",
      "中文名稱": "貝芬替",
      "農藥代號": "F066",
      "英文名稱": "CARBENDAZIM",
      "廠牌名稱": "大豐利",
      "化學成分": "methyl benzimidazol-2-ylcarbamate",
      "國外原製造廠商": "FOMOTHAI CORPORATION COMPANY LIMITED",
      "有效期限": "109/07/13",
      "廠商名稱": "蒙狄生股份有限公司",
      "農藥使用範圍": "http://data.coa.gov.tw:80/Service/OpenData/FromM/PesticideDetail.aspx?ltyp=20&lno=02464"
    },
    {
      "許可證字": "農藥進",
      "許可證號": "02471",
      "中文名稱": "貝芬替",
      "農藥代號": "F066",
      "英文名稱": "CARBENDAZIM",
      "廠牌名稱": "巴速汀",
      "化學成分": "methyl benzimidazol-2-ylcarbamate",
      "國外原製造廠商": "ALFA (SAIGON) COMPANY LIMITED",
      "有效期限": "109/07/31",
      "廠商名稱": "雅飛有限公司",
      "農藥使用範圍": "http://data.coa.gov.tw:80/Service/OpenData/FromM/PesticideDetail.aspx?ltyp=20&lno=02471"
    },
    {
      "許可證字": "農藥製",
      "許可證號": "02640",
      "中文名稱": "貝芬替",
      "農藥代號": "F066",
      "英文名稱": "CARBENDAZIM",
      "廠牌名稱": "大收產",
      "化學成分": "methyl benzimidazol-2-ylcarbamate",
      "國外原製造廠商": null,
      "有效期限": "110/03/27",
      "廠商名稱": "光華化學股份有限公司",
      "農藥使用範圍": "http://data.coa.gov.tw:80/Service/OpenData/FromM/PesticideDetail.aspx?ltyp=10&lno=02640"
    },
    {
      "許可證字": "農藥進",
      "許可證號": "02766",
      "中文名稱": "貝芬替",
      "農藥代號": "F066",
      "英文名稱": "CARBENDAZIM",
      "廠牌名稱": "農好百賜汀",
      "化學成分": "methyl benzimidazol-2-ylcarbamate",
      "國外原製造廠商": "AGROSMART LTD.",
      "有效期限": "109/09/30",
      "廠商名稱": "台灣瑪斯德股份有限公司",
      "農藥使用範圍": "http://data.coa.gov.tw:80/Service/OpenData/FromM/PesticideDetail.aspx?ltyp=20&lno=02766"
    }
  ],
  "usages": [
    {
      "作物名稱": "洋菇",
      "病蟲害名稱": "褐痘病",
      "每公頃使用用藥量": "1-2G/坪",
      "稀釋倍數": "1000-3000",
      "使用時期": "病害發生初期開始施藥",
      "施藥間隔": "-日",
      "安全採收期": "7日"
    },
    {
      "作物名稱": "菸草",
      "病蟲害名稱": "白星病",
      "每公頃使用用藥量": "0.5公斤",
      "稀釋倍數": "2000",
      "使用時期": "病害發生初期開始施藥",
      "施藥間隔": "-日",
      "安全採收期": "7日"
    },
    {
      "作物名稱": "菊",
      "病蟲害名稱": "莖腐病",
      "每公頃使用用藥量": "0.3-1公斤",
      "稀釋倍數": "1200",
      "使用時期": "扦插或分株後施藥1次",
      "施藥間隔": "-日",
      "安全採收期": "-日"
    },
    {
      "作物名稱": "菊",
      "病蟲害名稱": "莖腐病",
      "每公頃使用用藥量": "",
      "稀釋倍數": "1500",
      "使用時期": "扦插後施藥1次",
      "施藥間隔": "-日",
      "安全採收期": "-日"
    },
    {
      "作物名稱": "洋菇",
      "病蟲害名稱": "褐痘病",
      "每公頃使用用藥量": "0.8-1.7g/每坪",
      "稀釋倍數": "1200-3600",
      "使用時期": "病害發生初期開始施藥",
      "施藥間隔": "-日",
      "安全採收期": "-日"
    },
    {
      "作物名稱": "菊",
      "病蟲害名稱": "莖腐病",
      "每公頃使用用藥量": "0.3-1.2公升",
      "稀釋倍數": "1000",
      "使用時期": "扦插或分株後施藥1次，至全株濕潤",
      "施藥間隔": "-日",
      "安全採收期": "-日"
    },
    {
      "作物名稱": "葡萄",
      "病蟲害名稱": "黑痘病",
      "每公頃使用用藥量": "",
      "稀釋倍數": "2000",
      "使用時期": "病害發生初期開始施藥",
      "施藥間隔": "7-10日",
      "安全採收期": "21日"
    }
  ]
}
