{
  "id": "F221",
  "普通名稱": "賽普洛",
  "廠牌名稱": null,
  "通過日期": null,
  "licenses": [
    {
      "許可證字": "農藥原進",
      "許可證號": "00663",
      "中文名稱": "賽普洛",
      "農藥代號": "F221",
      "英文名稱": "CYPRODINIL",
      "廠牌名稱": null,
      "化學成分": "4-cyclopropyl-6-methyl-N-phenylpyrimidin-2-amine",
      "國外原製造廠商": "SYNGENTA CROP PROTECTION MONTHEY S.A.",
      "有效期限": "113/09/19",
      "廠商名稱": "台灣先正達股份有限公司",
      "農藥使用範圍": "http://data.coa.gov.tw:80/Service/OpenData/FromM/PesticideDetail.aspx?ltyp=40&lno=00663"
    },
    {
      "許可證字": "農藥進",
      "許可證號": "01736",
      "中文名稱": "賽普洛",
      "農藥代號": "F221",
      "英文名稱": "CYPRODINIL",
      "廠牌名稱": "霹靂馬",
      "化學成分": "4-cyclopropyl-6-methyl-N-phenylpyrimidin-2-amine",
      "國外原製造廠商": "EXWOLD TECHNOLOGY LIMITED",
      "有效期限": "112/03/12",
      "廠商名稱": "台灣先正達股份有限公司",
      "農藥使用範圍": "http://data.coa.gov.tw:80/Service/OpenData/FromM/PesticideDetail.aspx?ltyp=20&lno=01736"
    },
    {
      "許可證字": "農藥進",
      "許可證號": "02321",
      "中文名稱": "賽普洛",
      "農藥代號": "F221",
      "英文名稱": "CYPRODINIL",
      "廠牌名稱": "克百龍",
      "化學成分": "4-cyclopropyl-6-methyl-N-phenylpyrimidin-2-amine",
      "國外原製造廠商": "SYNGENTA KOREA LIMITED",
      "有效期限": "112/10/27",
      "廠商名稱": "台灣先正達股份有限公司",
      "農藥使用範圍": "http://data.coa.gov.tw:80/Service/OpenData/FromM/PesticideDetail.aspx?ltyp=20&lno=02321"
    }
  ],
  "usages": [
    {
      "作物名稱": "瓜果類",
      "病蟲害名稱": "白粉病",
      "每公頃使用用藥量": "0.6-0.8公斤",
      "稀釋倍數": "1500",
      "使用時期": "病害發生初期開始施藥",
      "施藥間隔": "7日",
      "安全採收期": "6日"
    },
    {
      "作物名稱": "瓜菜類",
      "病蟲害名稱": "白粉病",
      "每公頃使用用藥量": "0.6-0.8公斤",
      "稀釋倍數": "1500",
      "使用時期": "病害發生初期開始施藥",
      "施藥間隔": "7日",
      "安全採收期": "6日"
    },
    {
      "作物名稱": "花木",
      "病蟲害名稱": "白粉病",
      "每公頃使用用藥量": "0.4-1.7公斤",
      "稀釋倍數": "1,500",
      "使用時期": "病害發生初期開始施藥",
      "施藥間隔": "7日",
      "安全採收期": "日"
    },
    {
      "作物名稱": "桃",
      "病蟲害名稱": "褐腐病",
      "每公頃使用用藥量": "-",
      "稀釋倍數": "1000",
      "使用時期": "",
      "施藥間隔": "-日",
      "安全採收期": "6日"
    },
    {
      "作物名稱": "梨",
      "病蟲害名稱": "黑星病",
      "每公頃使用用藥量": "",
      "稀釋倍數": "1500",
      "使用時期": "病害發生初期開始施藥",
      "施藥間隔": "7日",
      "安全採收期": "12日"
    },
    {
      "作物名稱": "梨果類",
      "病蟲害名稱": "黑星病",
      "每公頃使用用藥量": "",
      "稀釋倍數": "1500",
      "使用時期": "病害發生初期開始施藥",
      "施藥間隔": "7日",
      "安全採收期": "12日"
    },
    {
      "作物名稱": "梨果類",
      "病蟲害名稱": "菌核病",
      "每公頃使用用藥量": "",
      "稀釋倍數": "1000",
      "使用時期": "萌蕾時及謝花後各施藥1次，結果後每隔10天施藥1次",
      "施藥間隔": "10日",
      "安全採收期": "6日"
    }
  ]
}
