{
  "id": "H014",
  "普通名稱": "二、四－地",
  "廠牌名稱": null,
  "通過日期": null,
  "licenses": [
    {
      "許可證字": "農藥原進",
      "許可證號": "00466",
      "中文名稱": "二、四－地",
      "農藥代號": "H014",
      "英文名稱": "2,4-D",
      "廠牌名稱": null,
      "化學成分": "(2,4-dichlorophenoxy)acetic acid",
      "國外原製造廠商": "KRISHI RASAYAN (ORISSA)",
      "有效期限": "109/09/11",
      "廠商名稱": "松樹國際有限公司",
      "農藥使用範圍": "http://data.coa.gov.tw:80/Service/OpenData/FromM/PesticideDetail.aspx?ltyp=40&lno=00466"
    },
    {
      "許可證字": "農藥原進",
      "許可證號": "00478",
      "中文名稱": "二、四－地",
      "農藥代號": "H014",
      "英文名稱": "2,4-D",
      "廠牌名稱": null,
      "化學成分": "(2,4-dichlorophenoxy)acetic acid",
      "國外原製造廠商": "KRISHI RASAYAN (BIHAR)",
      "有效期限": "109/11/25",
      "廠商名稱": "東鋒股份有限公司",
      "農藥使用範圍": "http://data.coa.gov.tw:80/Service/OpenData/FromM/PesticideDetail.aspx?ltyp=40&lno=00478"
    },
    {
      "許可證字": "農藥進",
      "許可證號": "00590",
      "中文名稱": "二、四－地",
      "農藥代號": "H014",
      "英文名稱": "2,4-D",
      "廠牌名稱": null,
      "化學成分": "(2,4-dichlorophenoxy)acetic acid",
      "國外原製造廠商": "ISHIHARA SANGYO KAISHA, LTD. YOKKAICHI PLANT",
      "有效期限": "109/09/12",
      "廠商名稱": "台灣石原產業股份有限公司",
      "農藥使用範圍": "http://data.coa.gov.tw:80/Service/OpenData/FromM/PesticideDetail.aspx?ltyp=20&lno=00590"
    },
    {
      "許可證字": "農藥原進",
      "許可證號": "01088",
      "中文名稱": "二、四－地",
      "農藥代號": "H014",
      "英文名稱": "2,4-D",
      "廠牌名稱": null,
      "化學成分": "(2,4-dichlorophenoxy)acetic acid",
      "國外原製造廠商": "JIANGSU GOOD HARVEST-WEIEN AGROCHEMICAL CO., LTD.",
      "有效期限": "112/07/31",
      "廠商名稱": "日農科技股份有限公司",
      "農藥使用範圍": "http://data.coa.gov.tw:80/Service/OpenData/FromM/PesticideDetail.aspx?ltyp=40&lno=01088"
    },
    {
      "許可證字": "農藥原進",
      "許可證號": "01107",
      "中文名稱": "二、四－地",
      "農藥代號": "H014",
      "英文名稱": "2,4-D",
      "廠牌名稱": null,
      "化學成分": "(2,4-dichlorophenoxy)acetic acid",
      "國外原製造廠商": "SHANDONG KEYUAN CHEMICAL CO., LTD",
      "有效期限": "112/10/29",
      "廠商名稱": "青山貿易有限公司",
      "農藥使用範圍": "http://data.coa.gov.tw:80/Service/OpenData/FromM/PesticideDetail.aspx?ltyp=40&lno=01107"
    },
    {
      "許可證字": "農藥原進",
      "許可證號": "01118",
      "中文名稱": "二、四－地",
      "農藥代號": "H014",
      "英文名稱": "2,4-D",
      "廠牌名稱": null,
      "化學成分": "(2,4-dichlorophenoxy)acetic acid",
      "國外原製造廠商": "JIANGSU WINTAFONE CROPSCIENCE CO., LTD.",
      "有效期限": "113/01/30",
      "廠商名稱": "日農科技股份有限公司",
      "農藥使用範圍": "http://data.coa.gov.tw:80/Service/OpenData/FromM/PesticideDetail.aspx?ltyp=40&lno=01118"
    },
    {
      "許可證字": "農藥製",
      "許可證號": "01941",
      "中文名稱": "二、四－地",
      "農藥代號": "H014",
      "英文名稱": "2,4-D",
      "廠牌名稱": "草多滅",
      "化學成分": "(2,4-dichlorophenoxy)acetic acid",
      "國外原製造廠商": null,
      "有效期限": "109/07/29",
      "廠商名稱": "龍燈生物科技股份有限公司",
      "農藥使用範圍": "http://data.coa.gov.tw:80/Service/OpenData/FromM/PesticideDetail.aspx?ltyp=10&lno=01941"
    },
    {
      "許可證字": "農藥製",
      "許可證號": "02032",
      "中文名稱": "二、四－地",
      "農藥代號": "H014",
      "英文名稱": "2,4-D",
      "廠牌名稱": "力除",
      "化學成分": "(2,4-dichlorophenoxy)acetic acid",
      "國外原製造廠商": null,
      "有效期限": "109/07/29",
      "廠商名稱": "興農股份有限公司",
      "農藥使用範圍": "http://data.coa.gov.tw:80/Service/OpenData/FromM/PesticideDetail.aspx?ltyp=10&lno=02032"
    },
    {
      "許可證字": "農藥製",
      "許可證號": "02654",
      "中文名稱": "二、四－地",
      "農藥代號": "H014",
      "英文名稱": "2,4-D",
      "廠牌名稱": "奧斯地",
      "化學成分": "(2,4-dichlorophenoxy)acetic acid",
      "國外原製造廠商": null,
      "有效期限": "110/05/02",
      "廠商名稱": "台灣正豐植保股份有限公司",
      "農藥使用範圍": "http://data.coa.gov.tw:80/Service/OpenData/FromM/PesticideDetail.aspx?ltyp=10&lno=02654"
    },
    {
      "許可證字": "農藥製",
      "許可證號": "02662",
      "中文名稱": "二、四－地",
      "農藥代號": "H014",
      "英文名稱": "2,4-D",
      "廠牌名稱": null,
      "化學成分": "(2,4-dichlorophenoxy)acetic acid",
      "國外原製造廠商": null,
      "有效期限": "110/02/21",
      "廠商名稱": "嘉農企業股份有限公司",
      "農藥使用範圍": "http://data.coa.gov.tw:80/Service/OpenData/FromM/PesticideDetail.aspx?ltyp=10&lno=02662"
    }
  ],
  "usages": [
    {
      "作物名稱": "甘蔗",
      "病蟲害名稱": "雜草",
      "每公頃使用用藥量": "2-3公斤",
      "稀釋倍數": "200-300",
      "使用時期": "植蔗後一個月",
      "施藥間隔": "日",
      "安全採收期": "日"
    }
  ]
}
