{
	"id": "F183",
	"name": "護粒松",
	"licenses": [
		{
			"許可證號": "00003",
			"化學成分": "O-ethyl S,S-diphenyl phosphorodithioate",
			"廠牌名稱": null,
			"國外原製造廠商": "SAE RYUNG CHEMICALS CO., LTD.",
			"有效期限": "112/11/04",
			"廠商名稱": "東鋒股份有限公司"
		},
		{
			"許可證號": "00017",
			"化學成分": "O-ethyl S,S-diphenyl phosphorodithioate",
			"廠牌名稱": null,
			"國外原製造廠商": null,
			"有效期限": "113/04/23",
			"廠商名稱": "功力化學工業股份有限公司"
		},
		{
			"許可證號": "00168",
			"化學成分": "O-ethyl S,S-diphenyl phosphorodithioate",
			"廠牌名稱": null,
			"國外原製造廠商": null,
			"有效期限": "111/12/16",
			"廠商名稱": "興農股份有限公司"
		},
		{
			"許可證號": "00241",
			"化學成分": "O-ethyl S,S-diphenyl phosphorodithioate",
			"廠牌名稱": "喜稻增",
			"國外原製造廠商": null,
			"有效期限": "113/01/29",
			"廠商名稱": "正農化學股份有限公司"
		},
		{
			"許可證號": "01002",
			"化學成分": "O-ethyl S,S-diphenyl phosphorodithioate",
			"廠牌名稱": "喜稻生",
			"國外原製造廠商": null,
			"有效期限": "108/12/30",
			"廠商名稱": "安旺特股份有限公司"
		},
		{
			"許可證號": "01205",
			"化學成分": "O-ethyl S,S-diphenyl phosphorodithioate",
			"廠牌名稱": null,
			"國外原製造廠商": null,
			"有效期限": "103/12/31",
			"廠商名稱": "建農化工廠股份有限公司"
		},
		{
			"許可證號": "01251",
			"化學成分": "O-ethyl S,S-diphenyl phosphorodithioate",
			"廠牌名稱": "喜多生",
			"國外原製造廠商": null,
			"有效期限": "108/12/31",
			"廠商名稱": "興農股份有限公司"
		},
		{
			"許可證號": "01592",
			"化學成分": "O-ethyl S,S-diphenyl phosphorodithioate",
			"廠牌名稱": null,
			"國外原製造廠商": null,
			"有效期限": "108/12/31",
			"廠商名稱": "中華民國農會附設各級農會農化廠"
		},
		{
			"許可證號": "01597",
			"化學成分": "O-ethyl S,S-diphenyl phosphorodithioate",
			"廠牌名稱": "喜多生",
			"國外原製造廠商": null,
			"有效期限": "109/03/31",
			"廠商名稱": "興農股份有限公司"
		},
		{
			"許可證號": "01754",
			"化學成分": "O-ethyl S,S-diphenyl phosphorodithioate",
			"廠牌名稱": "喜粒松",
			"國外原製造廠商": null,
			"有效期限": "108/12/31",
			"廠商名稱": "聯利農業科技股份有限公司"
		},
		{
			"許可證號": "01799",
			"化學成分": "O-ethyl S,S-diphenyl phosphorodithioate",
			"廠牌名稱": "臺綠生",
			"國外原製造廠商": null,
			"有效期限": "109/01/08",
			"廠商名稱": "臺益工業股份有限公司"
		},
		{
			"許可證號": "01852",
			"化學成分": "O-ethyl S,S-diphenyl phosphorodithioate",
			"廠牌名稱": null,
			"國外原製造廠商": null,
			"有效期限": "109/01/30",
			"廠商名稱": "惠光股份有限公司"
		},
		{
			"許可證號": "01882",
			"化學成分": "O-ethyl S,S-diphenyl phosphorodithioate",
			"廠牌名稱": "稻熱松",
			"國外原製造廠商": "VIETNAM PESTICIDE JOINT-STOCK COMPANY",
			"有效期限": "108/11/30",
			"廠商名稱": "瑞泓生技有限公司"
		},
		{
			"許可證號": "01918",
			"化學成分": "O-ethyl S,S-diphenyl phosphorodithioate",
			"廠牌名稱": "喜豐產",
			"國外原製造廠商": null,
			"有效期限": "108/12/31",
			"廠商名稱": "瑞芳植物保護股份有限公司"
		},
		{
			"許可證號": "02093",
			"化學成分": "O-ethyl S,S-diphenyl phosphorodithioate",
			"廠牌名稱": "嘉穩收",
			"國外原製造廠商": null,
			"有效期限": "109/04/03",
			"廠商名稱": "嘉農企業股份有限公司"
		},
		{
			"許可證號": "02168",
			"化學成分": "O-ethyl S,S-diphenyl phosphorodithioate",
			"廠牌名稱": null,
			"國外原製造廠商": null,
			"有效期限": "109/04/30",
			"廠商名稱": "光華化學股份有限公司"
		},
		{
			"許可證號": "02264",
			"化學成分": "O-ethyl S,S-diphenyl phosphorodithioate",
			"廠牌名稱": "顧穗寶",
			"國外原製造廠商": null,
			"有效期限": "109/05/29",
			"廠商名稱": "富農化學工業股份有限公司"
		},
		{
			"許可證號": "02477",
			"化學成分": "O-ethyl S,S-diphenyl phosphorodithioate",
			"廠牌名稱": "永得勝",
			"國外原製造廠商": null,
			"有效期限": "109/08/28",
			"廠商名稱": "洽益化學股份有限公司"
		}
	],
	"英文名稱": "EDIFENPHOS",
	"作用機制": "[FRAC] 6, F2",
	"廠牌名稱": null,
	"通過日期": null,
	"usages": [
		{
			"作物名稱": "水稻",
			"病蟲害名稱": "葉稻熱病",
			"每公頃使用用藥量": "1公升",
			"稀釋倍數": "1000",
			"使用時期": "插秧後施藥",
			"施藥間隔": "-日",
			"安全採收期": "21日"
		},
		{
			"作物名稱": "水稻",
			"病蟲害名稱": "穗稻熱病",
			"每公頃使用用藥量": "1.2公升",
			"稀釋倍數": "1000",
			"使用時期": "",
			"施藥間隔": "-日",
			"安全採收期": "21日"
		},
		{
			"作物名稱": "水稻",
			"病蟲害名稱": "葉稻熱病",
			"每公頃使用用藥量": "1公升",
			"稀釋倍數": "250",
			"使用時期": "",
			"施藥間隔": "日",
			"安全採收期": "21日"
		},
		{
			"作物名稱": "水稻",
			"病蟲害名稱": "穗稻熱病",
			"每公頃使用用藥量": "1.2公升",
			"稀釋倍數": "250",
			"使用時期": "",
			"施藥間隔": "日",
			"安全採收期": "21日"
		},
		{
			"作物名稱": "水稻",
			"病蟲害名稱": "葉稻熱病",
			"每公頃使用用藥量": "1公升",
			"稀釋倍數": "",
			"使用時期": "",
			"施藥間隔": "-日",
			"安全採收期": "21日"
		},
		{
			"作物名稱": "水稻",
			"病蟲害名稱": "穗稻熱病",
			"每公頃使用用藥量": "1公升",
			"稀釋倍數": "",
			"使用時期": "",
			"施藥間隔": "-日",
			"安全採收期": "21日"
		}
	]
}