{
	"id": "I213",
	"name": "芬普尼",
	"licenses": [
		{
			"許可證號": "00829",
			"化學成分": "(±)-5-amino-1-(2,6-dichloro-α,α,α-trifluoro-p-tolyl) -4-trifluoromethylsulfinylpyrazole-3-carbonitrile",
			"廠牌名稱": "火龍寶丹",
			"國外原製造廠商": "COROMANDEL INTERNATIONAL LIMITED",
			"有效期限": "109/06/28",
			"廠商名稱": "美商雅柏生活科技有限公司臺灣分公司"
		},
		{
			"許可證號": "00868",
			"化學成分": "(±)-5-amino-1-(2,6-dichloro-α,α,α-trifluoro-p-tolyl) -4-trifluoromethylsulfinylpyrazole-3-carbonitrile",
			"廠牌名稱": null,
			"國外原製造廠商": "GSP CROP SCIENCE PRIVATE LIMITED",
			"有效期限": "112/07/03",
			"廠商名稱": "雅飛有限公司"
		},
		{
			"許可證號": "00871",
			"化學成分": "(±)-5-amino-1-(2,6-dichloro-α,α,α-trifluoro-p-tolyl) -4-trifluoromethylsulfinylpyrazole-3-carbonitrile",
			"廠牌名稱": null,
			"國外原製造廠商": "NINGBO SUNJOY AGROSCIENCE CO., LTD.",
			"有效期限": "112/08/01",
			"廠商名稱": "育禾化學興業有限公司"
		},
		{
			"許可證號": "00953",
			"化學成分": "(±)-5-amino-1-(2,6-dichloro-α,α,α-trifluoro-p-tolyl) -4-trifluoromethylsulfinylpyrazole-3-carbonitrile",
			"廠牌名稱": null,
			"國外原製造廠商": "HEBEI SANLEN AGROCHEMICAL CO., LTD.",
			"有效期限": "109/10/04",
			"廠商名稱": "青山貿易有限公司"
		},
		{
			"許可證號": "01009",
			"化學成分": "(±)-5-amino-1-(2,6-dichloro-α,α,α-trifluoro-p-tolyl) -4-trifluoromethylsulfinylpyrazole-3-carbonitrile",
			"廠牌名稱": null,
			"國外原製造廠商": "JIANGSU TUOQIU AGROCHEMICALS CO., LTD.",
			"有效期限": "110/11/29",
			"廠商名稱": "日農科技股份有限公司"
		},
		{
			"許可證號": "01735",
			"化學成分": "(±)-5-amino-1-(2,6-dichloro-α,α,α-trifluoro-p-tolyl) -4-trifluoromethylsulfinylpyrazole-3-carbonitrile",
			"廠牌名稱": "戰將",
			"國外原製造廠商": "BAYER CROPSCIENCE LIMITED",
			"有效期限": "107/03/04",
			"廠商名稱": "台灣拜耳股份有限公司"
		},
		{
			"許可證號": "01797",
			"化學成分": "(±)-5-amino-1-(2,6-dichloro-α,α,α-trifluoro-p-tolyl) -4-trifluoromethylsulfinylpyrazole-3-carbonitrile",
			"廠牌名稱": "法台寶",
			"國外原製造廠商": "BAYER VIETNAM LTD. (BVL)",
			"有效期限": "112/12/23",
			"廠商名稱": "台灣拜耳股份有限公司"
		},
		{
			"許可證號": "02145",
			"化學成分": "(±)-5-amino-1-(2,6-dichloro-α,α,α-trifluoro-p-tolyl) -4-trifluoromethylsulfinylpyrazole-3-carbonitrile",
			"廠牌名稱": "法台寶",
			"國外原製造廠商": "BAYER VIETNAM LTD. (BVL)",
			"有效期限": "108/08/06",
			"廠商名稱": "台灣拜耳股份有限公司"
		},
		{
			"許可證號": "02575",
			"化學成分": "(±)-5-amino-1-(2,6-dichloro-α,α,α-trifluoro-p-tolyl) -4-trifluoromethylsulfinylpyrazole-3-carbonitrile",
			"廠牌名稱": "襲蟻長效型粒劑",
			"國外原製造廠商": "CONTRACT PACKAGING INC",
			"有效期限": "110/07/01",
			"廠商名稱": "台灣拜耳股份有限公司"
		},
		{
			"許可證號": "02646",
			"化學成分": "(±)-5-amino-1-(2,6-dichloro-α,α,α-trifluoro-p-tolyl) -4-trifluoromethylsulfinylpyrazole-3-carbonitrile",
			"廠牌名稱": "易級寶",
			"國外原製造廠商": "THE SCIENTIFIC FERTILISER CO., LTD.",
			"有效期限": "107/07/07",
			"廠商名稱": "易利特開發有限公司"
		},
		{
			"許可證號": "02664",
			"化學成分": "(±)-5-amino-1-(2,6-dichloro-α,α,α-trifluoro-p-tolyl) -4-trifluoromethylsulfinylpyrazole-3-carbonitrile",
			"廠牌名稱": "戰將",
			"國外原製造廠商": "BAYER CROPSCIENCE LTD",
			"有效期限": "112/12/01",
			"廠商名稱": "台灣拜耳股份有限公司"
		},
		{
			"許可證號": "02723",
			"化學成分": "(±)-5-amino-1-(2,6-dichloro-α,α,α-trifluoro-p-tolyl) -4-trifluoromethylsulfinylpyrazole-3-carbonitrile",
			"廠牌名稱": "農好寶",
			"國外原製造廠商": "AGROSMART LTD.",
			"有效期限": "108/11/05",
			"廠商名稱": "台灣瑪斯德股份有限公司"
		},
		{
			"許可證號": "02730",
			"化學成分": "(±)-5-amino-1-(2,6-dichloro-α,α,α-trifluoro-p-tolyl) -4-trifluoromethylsulfinylpyrazole-3-carbonitrile",
			"廠牌名稱": "剋螟寶",
			"國外原製造廠商": "COROMANDEL INTERNATIONAL LIMITED",
			"有效期限": "109/01/04",
			"廠商名稱": "國寶國際有限公司"
		},
		{
			"許可證號": "02732",
			"化學成分": "(±)-5-amino-1-(2,6-dichloro-α,α,α-trifluoro-p-tolyl) -4-trifluoromethylsulfinylpyrazole-3-carbonitrile",
			"廠牌名稱": "螟蟲絕",
			"國外原製造廠商": "COROMANDEL INTERNATIONAL LIMITED",
			"有效期限": "109/01/05",
			"廠商名稱": "美商雅柏生活科技有限公司臺灣分公司"
		},
		{
			"許可證號": "02741",
			"化學成分": "(±)-5-amino-1-(2,6-dichloro-α,α,α-trifluoro-p-tolyl) -4-trifluoromethylsulfinylpyrazole-3-carbonitrile",
			"廠牌名稱": "雄寶",
			"國外原製造廠商": "PARIJAT INDUSTRIES (INDIA) PVT. LTD.",
			"有效期限": "109/04/21",
			"廠商名稱": "台灣日產化工股份有限公司"
		},
		{
			"許可證號": "02778",
			"化學成分": "(±)-5-amino-1-(2,6-dichloro-α,α,α-trifluoro-p-tolyl) -4-trifluoromethylsulfinylpyrazole-3-carbonitrile",
			"廠牌名稱": "地上王",
			"國外原製造廠商": "PARIJAT INDUSTRIES (INDIA) PVT. LTD.",
			"有效期限": "109/11/29",
			"廠商名稱": "貝士得開發企業有限公司"
		}
	],
	"英文名稱": "FIPRONIL",
	"作用機制": "[IRAC] 2B",
	"廠牌名稱": "火龍寶丹",
	"通過日期": null,
	"usages": [
		{
			"作物名稱": "水稻",
			"病蟲害名稱": "瘤野螟",
			"每公頃使用用藥量": "120公克/箱(60*30*4公分)",
			"稀釋倍數": "-",
			"使用時期": "插秧前24小時",
			"施藥間隔": "-日",
			"安全採收期": "-日"
		},
		{
			"作物名稱": "水稻",
			"病蟲害名稱": "一點螟蟲",
			"每公頃使用用藥量": "20公斤",
			"稀釋倍數": "-",
			"使用時期": "分蘗期及孕穗末期各施藥1次",
			"施藥間隔": "-日",
			"安全採收期": "-日"
		},
		{
			"作物名稱": "水稻",
			"病蟲害名稱": "大螟",
			"每公頃使用用藥量": "20公斤",
			"稀釋倍數": "-",
			"使用時期": "分蘗期及孕穗末期各施藥1次",
			"施藥間隔": "-日",
			"安全採收期": "-日"
		},
		{
			"作物名稱": "水稻",
			"病蟲害名稱": "線蟲白尖病",
			"每公頃使用用藥量": "每育苗箱50g",
			"稀釋倍數": "",
			"使用時期": "",
			"施藥間隔": "-日",
			"安全採收期": "-日"
		},
		{
			"作物名稱": "水稻",
			"病蟲害名稱": "褐飛蝨",
			"每公頃使用用藥量": "每箱120公克",
			"稀釋倍數": "-",
			"使用時期": "插秧前24小時",
			"施藥間隔": "-日",
			"安全採收期": "-日"
		},
		{
			"作物名稱": "水稻",
			"病蟲害名稱": "二化螟蟲",
			"每公頃使用用藥量": "20公斤",
			"稀釋倍數": "",
			"使用時期": "分蘗期,孕穗末期施藥1次",
			"施藥間隔": "-日",
			"安全採收期": "-日"
		},
		{
			"作物名稱": "水稻",
			"病蟲害名稱": "水象鼻蟲",
			"每公頃使用用藥量": "120公克/箱(60*30*4公分)",
			"稀釋倍數": "-",
			"使用時期": "於機械插秧前24小時",
			"施藥間隔": "-日",
			"安全採收期": "-日"
		},
		{
			"作物名稱": "水稻",
			"病蟲害名稱": "二化螟蟲",
			"每公頃使用用藥量": "每箱120公克",
			"稀釋倍數": "-",
			"使用時期": "插秧前24小時",
			"施藥間隔": "-日",
			"安全採收期": "-日"
		},
		{
			"作物名稱": "玉米",
			"病蟲害名稱": "玉米螟",
			"每公頃使用用藥量": "20公斤",
			"稀釋倍數": "",
			"使用時期": "生育初期及雄花抽穗前施藥",
			"施藥間隔": "-日",
			"安全採收期": "15日"
		},
		{
			"作物名稱": "作物園",
			"病蟲害名稱": "紅火蟻",
			"每公頃使用用藥量": "95公斤",
			"稀釋倍數": "",
			"使用時期": "",
			"施藥間隔": "日",
			"安全採收期": "日"
		}
	]
}